chemcomp_loader/__init__.py
chemcomp_loader/chemistry_properties.py
chemcomp_loader/disc_loader.py
chemcomp_loader/import_config.py
chemcomp_loader/planet_loader.py
chemcomp_loader-0.4.7.dist-info/LICENSE
chemcomp_loader-0.4.7.dist-info/LICENSE.txt
chemcomp_loader-0.4.7.dist-info/METADATA
chemcomp_loader-0.4.7.dist-info/WHEEL
chemcomp_loader-0.4.7.dist-info/top_level.txt
chemcomp_loader-0.4.7.dist-info/RECORD
