Metadata-Version: 2.1
Name: chemcomp-loader
Version: 0.4.7
Summary: Load disc and planet data from chemcomp simulations.
Author: Joe Williams
Author-email: joepw1@hotmail.com
Keywords: python,chemcomp
Classifier: Development Status :: 3 - Alpha
Classifier: Intended Audience :: Education
Classifier: Programming Language :: Python :: 2
Classifier: Programming Language :: Python :: 3
Classifier: Operating System :: MacOS :: MacOS X
Classifier: Topic :: Scientific/Engineering :: Astronomy
License-File: LICENSE
License-File: LICENSE.txt
Requires-Dist: tables
Requires-Dist: numpy
Requires-Dist: matplotlib
Requires-Dist: astropy
